{
  "collectionName": "components_layout_hero_sections",
  "info": {
    "displayName": "HeroSection",
    "icon": "apple-alt",
    "description": ""
  },
  "options": {},
  "attributes": {
    "ImageGalleryExample": {
      "type": "media",
      "multiple": true,
      "required": false,
      "allowedTypes": [
        "images",
        "files",
        "videos",
        "audios"
      ]
    },
    "CallToActionText": {
      "type": "string",
      "required": true
    },
    "Buttons": {
      "type": "component",
      "repeatable": true,
      "component": "layout.button"
    }
  }
}
